uniview/__init__.py
uniview/im2d/__init__.py
uniview/im2d/image_data.py
uniview/vmo/__init__.py
uniview/vmo/bbox.py
uniview/vmo/constants.py
uniview/vmo/keypoints.py
uniview/vmo/person_profile.py
uniview-0.1.1.dist-info/entry_points.txt
uniview-0.1.1.dist-info/WHEEL
uniview-0.1.1.dist-info/METADATA
uniview-0.1.1.dist-info/RECORD
